{"8 Ср":{"11:00 - 13:00":{"2":"Селецкая Тамара","3":"Валентина Резанова","4":"Порохня Инна","5":"Рославец Людмила"}},"9 Чт":{"14:00 - 16:00":{"2":"Валентина Резанова","3":"Доценко Нина","4":"Сиз Ольга","5":"Лихицкая Любовь"}},"10 Пт":{"12:00 - 14:00":{"2":"Орехова Светлана","3":"Евграфова Светлана","4":"Порохня Инна","5":"Ольга Смиян"}},"11 Сб":{"13:00 - 15:00":{"3":"Алла Серикова","4":"Рославец Людмила","5":"Селецкая Тамара"}},"13 Пн":{"10:00 - 12:00":{"3":"Шепель Таня"}},"14 Вт":{"8:00 - 10:00":{"2":"Орехова Светлана","3":"Храмцова Виктория","4":"Селецкая Тамара","5":"Доценко Нина"},"14:00 - 16:00":{"2":"Валентина Резанова","3":"Доценко Нина","4":"Рославец Людмила","5":"Евграфова Светлана"}},"15 Ср":{"11:00 - 13:00":{"2":"Рупенко Лидия","3":"Валентина Резанова","4":"Порохня Инна","5":"Рославец Людмила"}},"16 Чт":{"14:00 - 16:00":{"2":"Валентина Резанова","3":"Доценко Нина","4":"Сиз Ольга"}},"17 Пт":{"12:00 - 14:00":{"2":"Орехова Светлана","3":"Евграфова Светлана","4":"Порохня Инна","5":"Ольга Смиян"}},"18 Сб":{"13:00 - 15:00":{"3":"Алла Серикова","4":"Рославец Людмила"}},"21 Вт":{"8:00 - 10:00":{"2":"Орехова Светлана","3":"Храмцова Виктория","4":"Селецкая Тамара","5":"Доценко Нина"},"14:00 - 16:00":{"2":"Валентина Резанова","3":"Доценко Нина","4":"Рославец Людмила","5":"Евграфова Светлана"}},"22 Ср":{"11:00 - 13:00":{"3":"Валентина Резанова","4":"Порохня Инна","5":"Рославец Людмила"}},"23 Чт":{"14:00 - 16:00":{"2":"Валентина Резанова","3":"Доценко Нина","4":"Сиз Ольга"}},"24 Пт":{"12:00 - 14:00":{"2":"Орехова Светлана","3":"Евграфова Светлана","4":"Порохня Инна","5":"Ольга Смиян"}},"25 Сб":{"13:00 - 15:00":{"3":"Алла Серикова","4":"Рославец Людмила"}},"28 Вт":{"8:00 - 10:00":{"2":"Орехова Светлана","3":"Храмцова Виктория","4":"Селецкая Тамара","5":"Доценко Нина"},"14:00 - 16:00":{"2":"Валентина Резанова","3":"Доценко Нина","4":"Рославец Людмила","5":"Евграфова Светлана"}},"29 Ср":{"11:00 - 13:00":{"3":"Валентина Резанова","4":"Порохня Инна","5":"Рославец Людмила"}},"30 Чт":{"14:00 - 16:00":{"2":"Валентина Резанова","3":"Доценко Нина","4":"Сиз Ольга"}},"31 Пт":{"12:00 - 14:00":{"2":"Орехова Светлана","3":"Евграфова Светлана","4":"Порохня Инна","5":"Ольга Смиян"}}}